bmiTestYJ/bmi.py
bmiTestYJ-0.0.0.3.dist-info/METADATA
bmiTestYJ-0.0.0.3.dist-info/WHEEL
bmiTestYJ-0.0.0.3.dist-info/top_level.txt
bmiTestYJ-0.0.0.3.dist-info/RECORD
