Metadata-Version: 2.1
Name: bmiTestYJ
Version: 0.0.0.3
Summary: My BMI Test Package
Home-page: https://blog.naver.com/rntmfrrnprl
Author: yeonju Choi
Author-email: rntmfrrnprl@gmail.com
License: MIT
Platform: UNKNOWN
Requires-Python: >=3
